{
  "configurePresets": [
    {
      "binaryDir": "${sourceDir}/build/${presetName}",
      "cacheVariables": {
        "BUILD_TESTING": "ON",
        "CMAKE_BUILD_TYPE": "Debug",
        "CMAKE_EXPORT_COMPILE_COMMANDS": "YES",
        "CMAKE_TOOLCHAIN_FILE": "$env{VCPKG_ROOT}/scripts/buildsystems/vcpkg.cmake"
      },
      "generator": "Ninja",
      "hidden": true,
      "name": "base"
    },
    {
      "architecture": {
        "strategy": "external",
        "value": "x64"
      },
      "cacheVariables": {
        "CMAKE_PREFIX_PATH": "$env{QT6_X64_PATH}"
      },
      "displayName": "Win: Qt6 x64 Ninja",
      "inherits": ["base"],
      "name": "win-qt6-x64"
    },
    {
      "architecture": {
        "strategy": "external",
        "value": "x64"
      },
      "cacheVariables": {
        "CMAKE_PREFIX_PATH": "$env{QT5_X64_PATH}"
      },
      "displayName": "Win: Qt5 x64 Ninja",
      "inherits": ["base"],
      "name": "win-qt5-x64"
    },
    {
      "architecture": {
        "strategy": "external",
        "value": "x86"
      },
      "cacheVariables": {
        "CMAKE_PREFIX_PATH": "$env{QT6_X86_PATH}"
      },
      "displayName": "Win: Qt6 x86 Ninja",
      "inherits": ["base"],
      "name": "win-qt6-x86"
    },
    {
      "architecture": {
        "strategy": "external",
        "value": "x86"
      },
      "cacheVariables": {
        "CMAKE_PREFIX_PATH": "$env{QT5_X86_PATH}"
      },
      "displayName": "Win: Qt5 x86 Ninja",
      "inherits": ["base"],
      "name": "win-qt5-x86"
    },
    {
      "cacheVariables": {
        "CMAKE_CXX_COMPILER": "$env{MINGW_BIN_PATH}/g++.exe",
        "CMAKE_C_COMPILER": "$env{MINGW_BIN_PATH}/gcc.exe",
        "CMAKE_PREFIX_PATH": "$env{MINGW_X64_PATH}"
      },
      "displayName": "Win: MinGW x64",
      "environment": {
        "PATH": "$env{MINGW_BIN_PATH};$penv{PATH}"
      },
      "inherits": ["base"],
      "name": "win-mingw-x64"
    },
    {
      "cacheVariables": {
        "CMAKE_PREFIX_PATH": "$env{LINUX_QT_PATH}"
      },
      "condition": {
        "lhs": "${hostSystemName}",
        "rhs": "Linux",
        "type": "equals"
      },
      "displayName": "Linux: Qt6 x64",
      "inherits": ["base"],
      "name": "linux-x64"
    },
    {
      "architecture": {
        "strategy": "external",
        "value": "x64"
      },
      "cacheVariables": {
        "CMAKE_PREFIX_PATH": "$env{QT6_X64_PATH}"
      },
      "displayName": "Win: Qt6 x64 MSVC",
      "generator": "Visual Studio 17 2022",
      "inherits": ["base"],
      "name": "win-msvc-qt6-x64"
    },
    {
      "architecture": {
        "strategy": "external",
        "value": "x64"
      },
      "cacheVariables": {
        "CMAKE_PREFIX_PATH": "$env{QT5_X64_PATH}"
      },
      "displayName": "Win: Qt5 x64 MSVC",
      "generator": "Visual Studio 16 2019",
      "inherits": ["base"],
      "name": "win-msvc-qt5-x64"
    },
    {
      "architecture": {
        "strategy": "external",
        "value": "x86"
      },
      "cacheVariables": {
        "CMAKE_PREFIX_PATH": "$env{QT6_X86_PATH}"
      },
      "displayName": "Win: Qt6 x86 MSVC",
      "generator": "Visual Studio 17 2022",
      "inherits": ["base"],
      "name": "win-msvc-qt6-x86"
    },
    {
      "architecture": {
        "strategy": "external",
        "value": "x86"
      },
      "cacheVariables": {
        "CMAKE_PREFIX_PATH": "$env{QT5_X86_PATH}"
      },
      "displayName": "Win: Qt5 x86 MSVC",
      "generator": "Visual Studio 16 2019",
      "inherits": ["base"],
      "name": "win-msvc-qt5-x86"
    },
    {
      "architecture": {
        "strategy": "external",
        "value": "x86"
      },
      "cacheVariables": {
        "CMAKE_CXX_COMPILER": "$env{MINGW_BIN_PATH}/g++.exe",
        "CMAKE_C_COMPILER": "$env{MINGW_BIN_PATH}/gcc.exe",
        "CMAKE_PREFIX_PATH": "$env{MINGW_X64_PATH}"
      },
      "displayName": "Win: MinGW x86",
      "environment": {
        "PATH": "$env{MINGW_BIN_PATH};$penv{PATH}"
      },
      "inherits": ["base"],
      "name": "win-mingw-x86"
    },
    {
      "architecture": {
        "strategy": "external",
        "value": "x86"
      },
      "cacheVariables": {
        "CMAKE_PREFIX_PATH": "$env{LINUX_QT_PATH}"
      },
      "condition": {
        "lhs": "${hostSystemName}",
        "rhs": "Linux",
        "type": "equals"
      },
      "displayName": "Linux: Qt6 x86",
      "inherits": ["base"],
      "name": "linux-x86"
    }
  ],
  "buildPresets": [
    {
      "name": "build-msvc-qt5-x64-debug",
      "displayName": "Build Debug (Win: Qt5 x64 MSVC)",
      "configurePreset": "win-msvc-qt5-x64",
      "configuration": "Debug",
      "description": "Builds the Debug configuration using the Visual Studio generator"
    },
    {
      "name": "build-msvc-qt5-x64-release",
      "displayName": "Build Release (Win: Qt5 x64 MSVC)",
      "configurePreset": "win-msvc-qt5-x64",
      "configuration": "Release",
      "description": "Builds the Release configuration using the Visual Studio generator"
    },
    {
      "name": "build-msvc-qt6-x64-debug",
      "displayName": "Build Debug (Win: Qt6 x64 MSVC)",
      "configurePreset": "win-msvc-qt6-x64",
      "configuration": "Debug",
      "description": "Builds the Debug configuration using the Visual Studio generator"
    },
    {
      "name": "build-ninja-qt5-x64",
      "displayName": "Build (Win: Qt5 x64 Ninja)",
      "configurePreset": "win-qt5-x64",
      "description": "Build using Ninja generator (single-config). Ensure configure preset uses Debug if needed."
    }
  ],
  "version": 3
}
